pytest_parallelize_tests.py
pytest_parallelize_tests-0.2.dist-info/LICENSE
pytest_parallelize_tests-0.2.dist-info/METADATA
pytest_parallelize_tests-0.2.dist-info/WHEEL
pytest_parallelize_tests-0.2.dist-info/entry_points.txt
pytest_parallelize_tests-0.2.dist-info/top_level.txt
pytest_parallelize_tests-0.2.dist-info/RECORD
